Workbook

Sheet Gastos mensuales
A1: Concepto | B1: Cantidad | C1: Costo unitario | D1: Subtotal | E1: Categoria | F1: Inicio
A2: Nómina | B2: 5 | C2: 50000 | D2: =C2*B2 -> 250000 | E2: Mensual | F2: 44562
A3: Marketing | B3: 1 | C3: 10000 | D3: =C3*B3 -> 10000 | E3: Mensual | F3: 44562
A4: Renta | B4: 1 | C4: 10000 | D4: =C4*B4 -> 10000 | E4: Mensual | F4: 44562
A5: Computadoras | B5: 5 | C5: 20000 | D5: =C5*B5 -> 100000 | E5: Una vez | F5: 44562
A6: Software | B6: 2 | C6: 5000 | D6: =C6*B6 -> 10000 | E6: Una vez | F6: 44562
A7: Legal | B7: 1 | C7: 10000 | D7: =C7*B7 -> 10000 | E7: Mensual | F7: 44562
A8: Contabilidad | B8: 1 | C8: 10000 | D8: =C8*B8 -> 10000 | E8: Mensual | F8: 44562
A9: Dominio | B9: 1 | C9: 1000 | D9: =C9*B9 -> 1000 | E9: Una vez | F9: 44562
A10: Cuentas de correo | B10: 5 | C10: 100 | D10: =C10*B10 -> 500 | E10: Mensual | F10: 44562
A11: Empleados variables | B11: 1 | C11: 20000 | D11: =C11*B11 -> 20000 | E11: Mensual | F11: 44562

Sheet Modelo
A1: Clientes al mes | B1: 2 | D1: Indicadores financieros
A2: Configuración | B2: 0 | D2: Tasa de descuento | F2: 0.3
A3: Renta | B3: 3500 | D3: Valor presente | F3: =NPV(F2/12,B25:Y25) -> -4277386.4
A4: Comisión 1 | B4: 0.2 | D4: TIR | F4: =IRR(B25:Y25)*12 -> #NUM!
A5: Comisión 2 | B5: 0.1
A6: Capital inicial (proy) | B6: =-1*SUMIF(B25:J25,"<0") -> 2511000
A7: Clientes por empleado | B7: 5
A8: Primeros clientes | B8: 45658
A10: Proyección
B11: 45658 | C11: 45689 | D11: 45717 | E11: 45748 | F11: 45778 | G11: 45809 | H11: 45839 | I11: 45870 | J11: 45901 | K11: 45931 | L11: 45962 | M11: 45992 | N11: 46023 | O11: 46054 | P11: 46082 | Q11: 46113 | R11: 46143 | S11: 46174 | T11: 46204 | U11: 46235 | V11: 46266 | W11: 46296 | X11: 46327 | Y11: 46357 | Z11: Total
A12: Clientes reales | B12: 2 | C12: 3 | D12: 3 | E12: 4 | F12: 4 | G12: 6 | H12: 7 | I12: 9 | J12: 9 | K12: 10 | L12: 10 | M12: 10 | N12: 14 | O12: 18 | P12: 20 | Q12: 22 | R12: 25 | S12: 30 | T12: 30 | U12: 30 | V12: 34 | W12: 37 | X12: 39 | Y12: 39 | Z12: =SUM(B12:Y12) -> 415
A13: Clientes proyectados | B13: =IF(B11=$B$8,$B$1,IF(B11>$B$8,#REF!+$B$1,0)) -> 2 | C13: =IF(C11=$B$8,$B$1,IF(C11>$B$8,B13+$B$1,0)) -> 4 | D13: =IF(D11=$B$8,$B$1,IF(D11>$B$8,C13+$B$1,0)) -> 6 | E13: =IF(E11=$B$8,$B$1,IF(E11>$B$8,D13+$B$1,0)) -> 8 | F13: =IF(F11=$B$8,$B$1,IF(F11>$B$8,E13+$B$1,0)) -> 10 | G13: =IF(G11=$B$8,$B$1,IF(G11>$B$8,F13+$B$1,0)) -> 12 | H13: =IF(H11=$B$8,$B$1,IF(H11>$B$8,G13+$B$1,0)) -> 14 | I13: =IF(I11=$B$8,$B$1,IF(I11>$B$8,H13+$B$1,0)) -> 16 | J13: =IF(J11=$B$8,$B$1,IF(J11>$B$8,I13+$B$1,0)) -> 18 | ... Y13: =IF(Y11=$B$8,$B$1,IF(Y11>$B$8,X13+$B$1,0)) -> 48 | Z13: =SUM(B13:Y13) -> 600
A14: Configuración | B14: =IF(B11>=$B$8,$B$1*$B$2,0) -> 0 | C14: =IF(C11>=$B$8,$B$1*$B$2,0) -> 0 | D14: =IF(D11>=$B$8,$B$1*$B$2,0) -> 0 | E14: =IF(E11>=$B$8,$B$1*$B$2,0) -> 0 | F14: =IF(F11>=$B$8,$B$1*$B$2,0) -> 0 | G14: =IF(G11>=$B$8,$B$1*$B$2,0) -> 0 | H14: =IF(H11>=$B$8,$B$1*$B$2,0) -> 0 | I14: =IF(I11>=$B$8,$B$1*$B$2,0) -> 0 | ... Y14: =IF(Y11>=$B$8,$B$1*$B$2,0) -> 0
A15: Rentas | B15: =B13*$B$3 -> 7000 | C15: =C13*$B$3 -> 14000 | D15: =D13*$B$3 -> 21000 | E15: =E13*$B$3 -> 28000 | F15: =F13*$B$3 -> 35000 | G15: =G13*$B$3 -> 42000 | H15: =H13*$B$3 -> 49000 | I15: =I13*$B$3 -> 56000 | ... Y15: =Y13*$B$3 -> 168000 | Z15: =SUM(B15:Y15) -> 2100000
A17: Comisiones conf | B17: =IF(B11>=$B$8,$B$2*$B$4*$B$1,0) -> 0 | C17: =IF(C11>=$B$8,$B$2*$B$4*$B$1,0) -> 0 | D17: =IF(D11>=$B$8,$B$2*$B$4*$B$1,0) -> 0 | E17: =IF(E11>=$B$8,$B$2*$B$4*$B$1,0) -> 0 | F17: =IF(F11>=$B$8,$B$2*$B$4*$B$1,0) -> 0 | G17: =IF(G11>=$B$8,$B$2*$B$4*$B$1,0) -> 0 | H17: =IF(H11>=$B$8,$B$2*$B$4*$B$1,0) -> 0 | I17: =IF(I11>=$B$8,$B$2*$B$4*$B$1,0) -> 0 | ... Y17: =IF(Y11>=$B$8,$B$2*$B$4*$B$1,0) -> 0
A18: Comisiones renta | B18: =IF(B11>=$B$8,$B$3*$B$5*B13,0) -> 700 | C18: =IF(C11>=$B$8,$B$3*$B$5*C13,0) -> 1400 | D18: =IF(D11>=$B$8,$B$3*$B$5*D13,0) -> 2100 | E18: =IF(E11>=$B$8,$B$3*$B$5*E13,0) -> 2800 | F18: =IF(F11>=$B$8,$B$3*$B$5*F13,0) -> 3500 | G18: =IF(G11>=$B$8,$B$3*$B$5*G13,0) -> 4200 | H18: =IF(H11>=$B$8,$B$3*$B$5*H13,0) -> 4900 | I18: =IF(I11>=$B$8,$B$3*$B$5*I13,0) -> 5600 | ... Y18: =IF(Y11>=$B$8,$B$3*$B$5*Y13,0) -> 16800 | Z18: =SUM(B18:Y18) -> 210000
A19: Gastos fijo | B19: =SUMIFS('Gastos mensuales'!$D$2:$D$50,'Gastos mensuales'!$F$2:$F$50,"<="&Modelo!B11,'Gastos mensuales'!$E$2:$E$50,"Mensual")+SUMIFS('Gastos mensuales'!$D$2:$D$50,'Gastos mensuales'!$F$2:$F$50,"="&Modelo!B11,'Gastos mensuales'!$E$2:$E$50,"Mensual") -> 310500 | C19: =SUMIFS('Gastos mensuales'!$D$2:$D$50,'Gastos mensuales'!$F$2:$F$50,"<="&Modelo!C11,'Gastos mensuales'!$E$2:$E$50,"Mensual")+SUMIFS('Gastos mensuales'!$D$2:$D$50,'Gastos mensuales'!$F$2:$F$50,"="&Modelo!C11,'Gastos mensuales'!$E$2:$E$50,"Mensual") -> 310500 | D19: =SUMIFS('Gastos mensuales'!$D$2:$D$50,'Gastos mensuales'!$F$2:$F$50,"<="&Modelo!D11,'Gastos mensuales'!$E$2:$E$50,"Mensual")+SUMIFS('Gastos mensuales'!$D$2:$D$50,'Gastos mensuales'!$F$2:$F$50,"="&Modelo!D11,'Gastos mensuales'!$E$2:$E$50,"Mensual") -> 310500 | E19: =SUMIFS('Gastos mensuales'!$D$2:$D$50,'Gastos mensuales'!$F$2:$F$50,"<="&Modelo!E11,'Gastos mensuales'!$E$2:$E$50,"Mensual")+SUMIFS('Gastos mensuales'!$D$2:$D$50,'Gastos mensuales'!$F$2:$F$50,"="&Modelo!E11,'Gastos mensuales'!$E$2:$E$50,"Mensual") -> 310500 | F19: =SUMIFS('Gastos mensuales'!$D$2:$D$50,'Gastos mensuales'!$F$2:$F$50,"<="&Modelo!F11,'Gastos mensuales'!$E$2:$E$50,"Mensual")+SUMIFS('Gastos mensuales'!$D$2:$D$50,'Gastos mensuales'!$F$2:$F$50,"="&Modelo!F11,'Gastos mensuales'!$E$2:$E$50,"Mensual") -> 310500 | G19: =SUMIFS('Gastos mensuales'!$D$2:$D$50,'Gastos mensuales'!$F$2:$F$50,"<="&Modelo!G11,'Gastos mensuales'!$E$2:$E$50,"Mensual")+SUMIFS('Gastos mensuales'!$D$2:$D$50,'Gastos mensuales'!$F$2:$F$50,"="&Modelo!G11,'Gastos mensuales'!$E$2:$E$50,"Mensual") -> 310500 | H19: =SUMIFS('Gastos mensuales'!$D$2:$D$50,'Gastos mensuales'!$F$2:$F$50,"<="&Modelo!H11,'Gastos mensuales'!$E$2:$E$50,"Mensual")+SUMIFS('Gastos mensuales'!$D$2:$D$50,'Gastos mensuales'!$F$2:$F$50,"="&Modelo!H11,'Gastos mensuales'!$E$2:$E$50,"Mensual") -> 310500 | I19: =SUMIFS('Gastos mensuales'!$D$2:$D$50,'Gastos mensuales'!$F$2:$F$50,"<="&Modelo!I11,'Gastos mensuales'!$E$2:$E$50,"Mensual")+SUMIFS('Gastos mensuales'!$D$2:$D$50,'Gastos mensuales'!$F$2:$F$50,"="&Modelo!I11,'Gastos mensuales'!$E$2:$E$50,"Mensual") -> 310500 | ... Y19: =SUMIFS('Gastos mensuales'!$D$2:$D$50,'Gastos mensuales'!$F$2:$F$50,"<="&Modelo!Y11,'Gastos mensuales'!$E$2:$E$50,"Mensual")+SUMIFS('Gastos mensuales'!$D$2:$D$50,'Gastos mensuales'!$F$2:$F$50,"="&Modelo!Y11,'Gastos mensuales'!$E$2:$E$50,"Mensual") -> 310500 | Z19: =SUM(B19:Y19) -> 7452000
A20: Gastos variables | B20: ='Gastos mensuales'!$D$11*B13/$B$7 -> 8000 | C20: ='Gastos mensuales'!$D$11*C13/$B$7 -> 16000 | D20: ='Gastos mensuales'!$D$11*D13/$B$7 -> 24000 | E20: ='Gastos mensuales'!$D$11*E13/$B$7 -> 32000 | F20: ='Gastos mensuales'!$D$11*F13/$B$7 -> 40000 | G20: ='Gastos mensuales'!$D$11*G13/$B$7 -> 48000 | H20: ='Gastos mensuales'!$D$11*H13/$B$7 -> 56000 | I20: ='Gastos mensuales'!$D$11*I13/$B$7 -> 64000 | ... Y20: ='Gastos mensuales'!$D$11*Y13/$B$7 -> 192000 | Z20: =SUM(B20:Y20) -> 2400000
A22: Total ingresos | B22: =B14+B15 -> 7000 | C22: =C14+C15 -> 14000 | D22: =D14+D15 -> 21000 | E22: =E14+E15 -> 28000 | F22: =F14+F15 -> 35000 | G22: =G14+G15 -> 42000 | H22: =H14+H15 -> 49000 | I22: =I14+I15 -> 56000 | ... Y22: =Y14+Y15 -> 168000 | Z22: =SUM(B22:Y22) -> 2100000
A23: Total gastos | B23: =B17+B18+B19 -> 311200 | C23: =C17+C18+C19 -> 311900 | D23: =D17+D18+D19 -> 312600 | E23: =E17+E18+E19 -> 313300 | F23: =F17+F18+F19 -> 314000 | G23: =G17+G18+G19 -> 314700 | H23: =H17+H18+H19 -> 315400 | I23: =I17+I18+I19 -> 316100 | ... Y23: =Y17+Y18+Y19 -> 327300 | Z23: =SUM(B23:Y23) -> 7662000
A25: Total | B25: =B22-B23 -> -304200 | C25: =C22-C23 -> -297900 | D25: =D22-D23 -> -291600 | E25: =E22-E23 -> -285300 | F25: =F22-F23 -> -279000 | G25: =G22-G23 -> -272700 | H25: =H22-H23 -> -266400 | I25: =I22-I23 -> -260100 | ... Y25: =Y22-Y23 -> -159300 | Z25: =SUM(B25:Y25) -> -5562000
